GATE_PARAMS.vh

`ifndef GATE_PARAMS_VH
`define GATE_PARAMS_VH


    localparam NUM_GATES = 32;

`endif

GATE_DEFINES.vh
`ifndef GATE_DEFINES_VH
`define GATE_DEFINES_VH

    `define NUM_GATES_DEF 48

`endif

buffer.sv
`include "GATE_PARAMS.vh"

module buffer #(parameter WIDTH = NUM_GATES)(
    input  logic [WIDTH-1:0] din,
    output logic [WIDTH-1:0] dout
);
    assign dout = din;
endmodule

tb_buffer_params.sv
`timescale 1ns/1ns

module tb_buffer_params;

    // `include "GATE_DEFINES.vh"
    `include "GATE_PARAMS.vh"

    localparam GATE_NUMS = NUM_GATES;

    // PARAMETERIZED INPUTS
    logic [GATE_NUMS-1:0] input_a;
    logic [GATE_NUMS-1:0] output_c;

    int error_count;
    int run_count;

    logic [GATE_NUMS - 1 : 0] seed; // Seed for randomization

    initial begin
        error_count = 0; // initialize error count
        run_count   = 10000; // initialize run count
    end

    // Clock (not required for a pure buffer, but kept since you already had it)
    logic clock;

    // Clock generator
    initial clock = 0;
    always #2 clock = ~clock; // 250 MHz equivalent

    // Instantiate DUT (example buffer)
    buffer #(
        .WIDTH(GATE_NUMS)
    ) dut (
        .din(input_a),
        .dout(output_c)
    );

    // ====================== self checking testbench ======================
    // Keep while-loop as requested
    task automatic apply_stimulus();
        logic [GATE_NUMS-1:0] value;

        seed = $urandom; // Randomize seed for each run
        value = $urandom(seed); // Get initial random value

        while (run_count != 0) begin
            run_count--;

            value   = $urandom();
            input_a = value;

            #1; // allow combinational settle

            // For a buffer: expected output == input
            if (output_c !== value) begin
                $display("ERROR @%0t : input_a=%0h expected=%0h output_c=%0h",
                         $time, value, value, output_c);
                error_count++;
            end
        end
    endtask

    // Call the task (this is what actually runs the self-check)
    initial begin
        input_a = '0;
        #5;

        apply_stimulus();

        if (error_count == 0)
            $display("=== PASS ===");
        else begin
            $display("=== FAIL : %0d errors ===", error_count);
            $fatal(1, "Self-checking TB failed");
        end

        $finish;
    end

    final begin
        $display("===============FINISH HAS BEEN CALLED=============================");
        $display("Final error count: %0d", error_count);
    end

    // Monitor
    // initial begin
    //     $monitor("Time=%0t | input_a=%0d output_c=%0d", $time, input_a, output_c);
    // end

    // Dump waves
    initial begin
        $dumpfile("tb_buffer.vcd");
        $dumpvars(0, tb_buffer_params);
    end

endmodule

tb_buffer.vcd
$date
	Sun Feb 08 02:32:00 2026
$end
$version
	ModelSim Version 2020.1
$end
$timescale
	1ns
$end

$scope module tb_buffer_params $end
$var parameter 32 ! NUM_GATES $end
$var parameter 32 " GATE_NUMS $end
$var reg 32 # input_a [31:0] $end
$var reg 32 $ output_c [31:0] $end
$var integer 32 % error_count $end
$var integer 32 & run_count $end
$var reg 32 ' seed [31:0] $end
$var reg 1 ( clock $end

$scope task apply_stimulus $end
$upscope $end

$scope module dut $end
$var parameter 32 ) WIDTH $end
$var wire 1 * din [31] $end
$var wire 1 + din [30] $end
$var wire 1 , din [29] $end
$var wire 1 - din [28] $end
$var wire 1 . din [27] $end
$var wire 1 / din [26] $end
$var wire 1 0 din [25] $end
$var wire 1 1 din [24] $end
$var wire 1 2 din [23] $end
$var wire 1 3 din [22] $end
$var wire 1 4 din [21] $end
$var wire 1 5 din [20] $end
$var wire 1 6 din [19] $end
$var wire 1 7 din [18] $end
$var wire 1 8 din [17] $end
$var wire 1 9 din [16] $end
$var wire 1 : din [15] $end
$var wire 1 ; din [14] $end
$var wire 1 < din [13] $end
$var wire 1 = din [12] $end
$var wire 1 > din [11] $end
$var wire 1 ? din [10] $end
$var wire 1 @ din [9] $end
$var wire 1 A din [8] $end
$var wire 1 B din [7] $end
$var wire 1 C din [6] $end
$var wire 1 D din [5] $end
$var wire 1 E din [4] $end
$var wire 1 F din [3] $end
$var wire 1 G din [2] $end
$var wire 1 H din [1] $end
$var wire 1 I din [0] $end
$var reg 32 J dout [31:0] $end
$upscope $end
$upscope $end
$enddefinitions $end
#0
$dumpvars
b0 #
b0 $
bx '
0(
b0 J
b100000 !
b100000 "
b100000 )
b0 %
b10011100010000 &
0I
0H
0G
0F
0E
0D
0C
0B
0A
0@
0?
0>
0=
0<
0;
0:
09
08
07
06
05
04
03
02
01
00
0/
0.
0-
0,
0+
0*
$end
#2
1(
#4
0(
#5
b11111011101101010010100110000110 '
b10011100001111 &
b11001110000011101000000100110 #
1H
1G
1D
1=
1;
1:
19
13
12
11
1.
1-
b11001110000011101000000100110 J
b11001110000011101000000100110 $
#6
1(
b10011100001110 &
b111011011100000001100110011111 #
1I
1F
1E
0D
1B
1A
1>
0;
0:
09
15
14
02
10
1,
b111011011100000001100110011111 J
b111011011100000001100110011111 $
#7
b10011100001101 &
b100011110110111100101001010111 #
0F
1C
0B
0A
1@
0=
1;
1:
19
18
16
04
12
0.
0-
b100011110110111100101001010111 J
b100011110110111100101001010111 $
#8
0(
b10011100001100 &
b11100000110101010011100110010000 #
0I
0H
0G
0C
1B
1A
0@
1=
1<
0;
0:
08
17
06
01
00
1+
1*
b11100000110101010011100110010000 J
b11100000110101010011100110010000 $
#9
b10011100001011 &
b10110011110111001110110011010000 #
1C
0A
1?
0=
1;
1:
09
16
11
10
1-
0+
b10110011110111001110110011010000 J
b10110011110111001110110011010000 $
#10
1(
b10011100001010 &
b10101101111100100110001100111100 #
1G
1F
1D
0C
0B
1A
1@
0?
0>
0:
18
07
06
14
00
1/
1.
0-
b10101101111100100110001100111100 J
b10101101111100100110001100111100 $
#11
b10011100001001 &
b101010101101110010110000000001 #
1I
0G
0F
0E
0D
0A
0@
1?
1>
0;
19
17
03
01
10
0/
0*
b101010101101110010110000000001 J
b101010101101110010110000000001 $
#12
0(
b10011100001000 &
b10001001001100000011000001000101 #
1G
1C
0?
0>
1=
09
08
07
02
11
00
0,
1*
b10001001001100000011000001000101 J
b10001001001100000011000001000101 $
#13
b10011100000111 &
b1101000001100000110001101001 #
0G
1F
1D
1?
1>
0=
0<
18
17
05
04
1/
0*
b1101000001100000110001101001 J
b1101000001100000110001101001 $
#14
1(
b10011100000110 &
b111010011110011101000011011001 #
1E
0D
1B
0?
0>
1=
1;
1:
19
08
07
16
15
14
13
01
10
0/
1-
1,
b111010011110011101000011011001 J
b111010011110011101000011011001 $
#15
b10011100000101 &
b10011001100110001010101000100011 #
1H
0F
0E
1D
0C
0B
1@
1>
0=
1<
0;
09
04
03
12
11
00
0,
1*
b10011001100110001010101000100011 J
b10011001100110001010101000100011 $
#16
0(
b10011100000100 &
b1101100101110110011001111011010 #
0I
1F
1E
0D
1C
1B
1A
0>
1=
0:
19
18
14
01
1/
0-
1,
1+
0*
b1101100101110110011001111011010 J
b1101100101110110011001111011010 $
#17
b10011100000011 &
b100011110011011101000000010000 #
0H
0F
0C
0B
0A
0@
0<
1;
1:
08
17
05
04
13
11
10
0/
0.
0+
b100011110011011101000000010000 J
b100011110011011101000000010000 $
#18
1(
b10011100000010 &
b11100111101100000111001010010101 #
1I
1G
1B
1@
1<
0:
09
07
06
15
14
03
1/
1+
1*
b11100111101100000111001010010101 J
b11100111101100000111001010010101 $
#19
b10011100000001 &
b11110011000000011000111011100000 #
0I
0G
0E
1D
1C
1?
1>
0=
0<
0;
1:
19
05
04
02
0/
1-
b11110011000000011000111011100000 J
b11110011000000011000111011100000 $
#20
0(
b10011100000000 &
b10001010011011011100000000111101 #
1I
1G
1F
1E
0C
0B
0@
0?
0>
1;
17
16
14
13
01
1.
0-
0,
0+
b10001010011011011100000000111101 J
b10001010011011011100000000111101 $
#21
b10011011111111 &
b1011000110011111101110101110 #
0I
1H
0E
1B
1A
1@
1>
1=
1<
07
15
04
03
11
0*
b1011000110011111101110101110 J
b1011000110011111101110101110 $
#22
1(
b10011011111110 &
b101010010101011000110011000110 #
0F
0D
1C
0A
0@
1?
0=
0<
0;
17
06
13
01
1,
b101010010101011000110011000110 J
b101010010101011000110011000110 $
#23
b10011011111101 &
b1001001011000101111100110010001 #
1I
0H
0G
1E
0C
1A
0?
1=
1<
1;
09
18
07
05
14
11
00
0,
1+
b1001001011000101111100110010001 J
b1001001011000101111100110010001 $
#24
0(
b10011011111100 &
b10111001001000000110100000010011 #
1H
0B
0A
0=
0:
08
03
1-
1,
0+
1*
b10111001001000000110100000010011 J
b10111001001000000110100000010011 $
#25
b10011011111011 &
b1100100010100000101000101111110 #
0I
1G
1F
1D
1C
1A
0>
1=
0<
15
04
13
01
1/
0.
0-
1+
0*
b1100100010100000101000101111110 J
b1100100010100000101000101111110 $
#26
1(
b10011011111010 &
b10011000001111111111110111010010 #
0G
0F
0D
1B
1?
1>
1<
1:
19
18
17
16
14
03
0/
1.
1-
0,
0+
1*
b10011000001111111111110111010010 J
b10011000001111111111110111010010 $
#27
b10011011111001 &
b110100011110101000010100011100 #
0H
1G
1F
0C
0B
0>
0=
0<
0;
09
07
13
1/
0.
1,
0*
b110100011110101000010100011100 J
b110100011110101000010100011100 $
#28
0(
b10011011111000 &
b10101101001111100110100111000101 #
1I
0F
0E
1C
1B
0?
1>
1<
1;
0:
17
03
11
1.
0-
1*
b10101101001111100110100111000101 J
b10101101001111100110100111000101 $
#29
b10011011110111 &
b11000010101001110011001001100001 #
0G
1D
0B
0A
1@
0>
1=
0;
19
06
05
12
01
10
0/
0.
0,
1+
b11000010101001110011001001100001 J
b11000010101001110011001001100001 $
#30
1(
b10011011110110 &
b11010111101101000000100101110100 #
0I
1G
1E
1A
0@
1>
0=
0<
09
08
15
11
1/
1-
b11010111101101000000100101110100 J
b11010111101101000000100101110100 $
#31
b10011011110101 &
b1011111110110011001001110001101 #
1I
1F
0E
0D
0C
1B
1@
0>
1=
1:
19
07
16
04
13
1.
0*
b1011111110110011001001110001101 J
b1011111110110011001001110001101 $
#32
0(
b10011011110100 &
b1001001000101001011001101101100 #
0I
1D
1C
0B
1<
09
17
06
03
02
00
0/
0-
b1001001000101001011001101101100 J
b1001001000101001011001101101100 $
#33
b10011011110011 &
b1101001001101100111110010110 #
1H
0F
1E
0D
0C
1B
1?
1>
0=
0<
1;
18
05
14
1/
0+
b1101001001101100111110010110 J
b1101001001101100111110010110 $
#34
1(
b10011011110010 &
b1100001101000101111111011001101 #
1I
0H
1F
0E
1C
0A
1=
1<
07
12
0/
0.
1,
1+
b1100001101000101111111011001101 J
b1100001101000101111111011001101 $
#35
b10011011110001 &
b10110100110010001001110110001000 #
0I
0G
0C
1A
0@
0<
0;
08
16
04
13
01
1/
1-
0+
1*
b10110100110010001001110110001000 J
b10110100110010001001110110001000 $
#36
0(
b10011011110000 &
b11100011101111100011001101010 #
1H
1D
1C
0B
0A
1@
0>
0=
1;
19
18
17
06
15
14
02
1.
0,
0*
b11100011101111100011001101010 J
b11100011101111100011001101010 $
#37
b10011011101111 &
b10000011111001110110100101011000 #
0H
1E
0D
1A
0@
0?
1>
1<
0:
05
12
11
10
0/
0.
0-
1*
b10000011111001110110100101011000 J
b10000011111001110110100101011000 $
#38
1(
b10011011101110 &
b1111001101000100000001010000100 #
1G
0F
0E
0C
1B
0A
1@
0>
0<
0;
09
07
03
00
1.
1-
1,
1+
0*
b1111001101000100000001010000100 J
b1111001101000100000001010000100 $
#39
b10011011101101 &
b10101011111111000100101100110101 #
1I
1E
1D
0B
1A
1>
1;
08
17
16
15
13
10
0-
0+
1*
b10101011111111000100101100110101 J
b10101011111111000100101100110101 $
#40
0(
b10011011101100 &
b1111100110101101110110110000000 #
0I
0G
0E
0D
1B
0@
1?
1<
1:
18
06
04
01
00
1/
1-
1+
0*
b1111100110101101110110110000000 J
b1111100110101101110110110000000 $
#41
b10011011101011 &
b10100011100011101111100011101 #
1I
1G
1F
1E
0B
1@
1=
0<
19
08
07
14
02
0.
0,
0+
b10100011100011101111100011101 J
b10100011100011101111100011101 $
#42
1(
b10011011101010 &
b101110100100110111101010110000 #
0I
0G
0F
1D
1B
0A
0?
1<
0:
18
04
03
12
10
1.
0-
1,
b101110100100110111101010110000 J
b101110100100110111101010110000 $
#43
b10011011101001 &
b110010111100101100011110000001 #
1I
0E
0D
1A
1?
0>
0=
0<
1:
09
14
13
0/
0.
1-
b110010111100101100011110000001 J
b110010111100101100011110000001 $
#44
0(
b10011011101000 &
b10110110111111010110001101111111 #
1H
1G
1F
1E
1D
1C
0B
0?
1<
0:
19
08
17
16
1/
1*
b10110110111111010110001101111111 J
b10110110111111010110001101111111 $
#45
b10011011100111 &
b10011101001001101000011100100100 #
0I
0H
0F
0E
0C
1?
0<
0;
1:
09
18
06
05
03
02
11
00
1.
0,
b10011101001001101000011100100100 J
b10011101001001101000011100100100 $
#46
1(
b10011011100110 &
b1110001001100010101000011100111 #
1I
1H
1C
1B
0A
0@
0?
1=
1;
0:
19
08
07
15
0/
0.
1,
1+
0*
b1110001001100010101000011100111 J
b1110001001100010101000011100111 $
#47
b10011011100101 &
b1101011101010010100111010111010 #
0I
0G
1F
1E
0C
1@
1?
1>
0=
16
05
12
10
1.
0-
b1101011101010010100111010111010 J
b1101011101010010100111010111010 $
#48
0(
b10011011100100 &
b1111011011100000001011010111011 #
1I
0>
1=
0;
09
06
15
13
02
1-
b1111011011100000001011010111011 J
b1111011011100000001011010111011 $
#49
b10011011100011 &
b1100110110011010111010001110110 #
0I
1G
0F
1C
0B
0@
1<
1;
19
17
16
05
04
12
01
1/
0.
0-
b1100110110011010111010001110110 J
b1100110110011010111010001110110 $
#50
1(
b10011011100010 &
b10100011101101110011111001101 #
1I
0H
1F
0E
0D
1B
1A
1@
0=
1:
09
18
06
15
14
02
00
1-
0,
0+
b10100011101101110011111001101 J
b10100011101101110011111001101 $
#51
b10011011100001 &
b11100111110010000110111101101 #
1D
0@
1>
0<
0;
0:
19
08
07
16
12
1.
b11100111110010000110111101101 J
b11100111110010000110111101101 $
#52
0(
b10011011100000 &
b10011001011101010011001010111000 #
0I
0G
1E
0C
0A
1@
0?
0>
1=
1<
17
06
02
11
0/
1*
b10011001011101010011001010111000 J
b10011001011101010011001010111000 $
#53
b10011011011111 &
b1010000010101000001101100011000 #
0D
0B
1A
1>
0<
09
04
01
0.
1+
0*
b1010000010101000001101100011000 J
b1010000010101000001101100011000 $
#54
1(
b10011011011110 &
b10001000010111000111001011010001 #
1I
0F
1C
1B
0A
0>
1<
1;
16
1.
0-
0+
1*
b10001000010111000111001011010001 J
b10001000010111000111001011010001 $
#55
b10011011011101 &
b10111100011011100101111010001010 #
0I
1H
1F
0E
0C
1?
1>
0<
18
05
14
1/
1-
1,
b10111100011011100101111010001010 J
b10111100011011100101111010001010 $
#56
0(
b10011011011100 &
b1000010000110111101110111111001 #
1I
0H
1E
1D
1C
1A
0@
1:
19
07
15
04
03
10
0/
0.
0-
0,
1+
0*
b1000010000110111101110111111001 J
b1000010000110111101110111111001 $
#57
b10011011011011 &
b10100100010011110110010111010010 #
0I
1H
0F
0D
0>
0=
1<
0:
17
05
13
00
1/
1,
0+
1*
b10100100010011110110010111010010 J
b10100100010011110110010111010010 $
#58
1(
b10011011011010 &
b11111111100111010010001010100110 #
1G
0E
1D
0C
0A
1@
0?
0;
08
15
03
12
11
10
1.
1-
1+
b11111111100111010010001010100110 J
b11111111100111010010001010100110 $
#59
b10011011011001 &
b101111100111100001111100110011 #
1I
0G
1E
0B
1A
1?
1>
1=
0<
09
18
0-
0+
0*
b101111100111100001111100110011 J
b101111100111100001111100110011 $
#60
0(
b10011011011000 &
b110000000000010011100100000010 #
0I
0E
0D
0@
0?
1<
19
08
07
06
05
02
01
00
0/
0.
1-
b110000000000010011100100000010 J
b110000000000010011100100000010 $
#61
b10011011010111 &
b11111010000101011101110101010000 #
0H
1E
1C
1?
0<
1;
1:
17
15
10
1.
1+
1*
b11111010000101011101110101010000 J
b11111010000101011101110101010000 $
#62
1(
b10011011010110 &
b10111100000110011011011010010101 #
1I
1G
0C
1B
0A
1@
0>
1<
0;
07
16
00
1/
0+
b10111100000110011011011010010101 J
b10111100000110011011011010010101 $
#63
b10011011010101 &
b1110111100111110001010011111000 #
0I
0G
1F
1D
1C
0@
0<
0:
18
17
12
11
10
0.
1+
0*
b1110111100111110001010011111000 J
b1110111100111110001010011111000 $
#64
0(
b10011011010100 &
b101000010101011101001000011 #
1I
1H
0F
0E
0D
0B
1@
0?
1>
1<
1:
09
07
05
02
00
0-
0,
0+
b101000010101011101001000011 J
b101000010101011101001000011 $
#65
b10011011010011 &
b10000100101111000110100110001011 #
1F
0C
1B
1A
0@
0=
1;
0:
08
17
15
14
12
01
1*
b10000100101111000110100110001011 J
b10000100101111000110100110001011 $
#66
1(
b10011011010010 &
b10010100001011101110011001111001 #
0H
1E
1D
1C
0B
0A
1@
1?
0>
1:
18
05
02
1-
b10010100001011101110011001111001 J
b10010100001011101110011001111001 $
#67
b10011011010001 &
b1100100110000100010110011101111 #
1H
1G
0E
1B
0@
1>
0;
0:
07
06
04
13
12
0-
1,
1+
0*
b1100100110000100010110011101111 J
b1100100110000100010110011101111 $
#68
0(
b10011011010000 &
b11110000000110011110101011000001 #
0H
0G
0F
0D
1@
0?
1;
1:
19
08
16
15
03
02
0/
1-
1*
b11110000000110011110101011000001 J
b11110000000110011110101011000001 $
#69
b10011011001111 &
b1110011100011011100010100011010 #
0I
1H
1F
1E
0C
0B
1A
0@
1?
0>
0<
17
05
12
11
10
0*
b1110011100011011100010100011010 J
b1110011100011011100010100011010 $
#70
1(
b10011011001110 &
b10100101010111000100000010111011 #
1I
1D
1B
0A
0?
0:
09
15
13
02
00
1/
0-
0+
1*
b10100101010111000100000010111011 J
b10100101010111000100000010111011 $
#71
b10011011001101 &
b1111001110111010001011000110110 #
0I
1G
0F
0B
1@
1?
1=
0;
19
12
0/
1.
1-
1+
0*
b1111001110111010001011000110110 J
b1111001110111010001011000110110 $
#72
0(
b10011011001100 &
b11011010101111101111011000000001 #
1I
0H
0G
0E
0D
1<
1;
1:
09
18
14
03
01
10
0,
1*
b11011010101111101111011000000001 J
b11011010101111101111011000000001 $
#73
b10011011001011 &
b1100110000110011000101100100010 #
0I
1H
1D
1A
0?
1>
0=
0<
0;
19
08
07
04
02
1/
0.
0-
1,
0*
b1100110000110011000101100100010 J
b1100110000110011000101100100010 $
#74
1(
b10011011001010 &
b1101110010011111011001100110000 #
0H
1E
0>
1=
1<
18
17
05
13
1.
b1101110010011111011001100110000 J
b1101110010011111011001100110000 $
#75
b10011011001001 &
b1011001111011101110100000000 #
0E
0D
0@
1?
1>
0<
1;
08
15
14
03
11
0/
0,
0+
b1011001111011101110100000000 J
b1011001111011101110100000000 $
#76
0(
b10011011001000 &
b111000110000101001001111011010 #
1H
1F
1E
1C
1B
1@
0?
0>
0;
09
18
07
06
05
04
13
12
01
00
1-
1,
b111000110000101001001111011010 J
b111000110000101001001111011010 $
#77
b10011011000111 &
b1101110111111011010010100010010 #
0F
0C
0B
0@
1?
0=
1<
19
08
17
16
15
14
10
1/
0-
1+
b1101110111111011010010100010010 J
b1101110111111011010010100010010 $
#78
1(
b10011011000110 &
b1101010000010110101110111010011 #
1I
1C
1B
1>
1=
0<
1;
0:
18
07
05
04
03
02
0/
b1101010000010110101110111010011 J
b1101010000010110101110111010011 $
#79
b10011011000101 &
b10000000011001001010110010100000 #
0I
0H
0E
1D
0C
0A
0=
1<
0;
1:
09
08
17
06
14
13
00
0.
0,
0+
1*
b10000000011001001010110010100000 J
b10000000011001001010110010100000 $
#80
0(
b10011011000100 &
b1011101101000100111011010101011 #
1I
1H
1F
1@
0>
1=
1;
0:
18
07
03
12
11
1/
1.
1-
1+
0*
b1011101101000100111011010101011 J
b1011101101000100111011010101011 $
#81
b10011011000011 &
b11011101001001101000000011011101 #
0H
1G
1E
0D
1C
0@
0?
0=
0<
0;
1:
17
02
1*
b11011101001001101000000011011101 J
b11011101001001101000000011011101 $
#82
1(
b10011011000010 &
b11111110110011111110001111100001 #
0G
0F
0E
1D
1A
1@
1<
1;
19
16
04
13
12
01
10
1,
b11111110110011111110001111100001 J
b11111110110011111110001111100001 $
#83
b10011011000001 &
b1011010011100101000101001001001 #
1F
0D
0B
0A
1>
0<
0;
09
07
06
15
14
02
0/
0,
0*
b1011010011100101000101001001001 J
b1011010011100101000101001001001 $
#84
0(
b10011011000000 &
b1110100001101111000011011100011 #
1H
0F
1D
1B
1?
0>
19
17
03
00
1/
0.
1,
b1110100001101111000011011100011 J
b1110100001101111000011011100011 $
#85
b10011010111111 &
b110010010000010110111110100 #
0I
0H
1G
1E
1A
0@
1>
1<
0:
09
08
07
16
05
04
13
10
0-
0,
0+
b110010010000010110111110100 J
b110010010000010110111110100 $
#86
1(
b10011010111110 &
b1111001100010000001011101101110 #
1H
1F
0E
0B
1@
0>
1=
0<
03
12
11
00
0/
1.
1-
1,
1+
b1111001100010000001011101101110 J
b1111001100010000001011101101110 $
#87
b10011010111101 &
b1110001101001111010000100100 #
0H
0F
0C
0A
0@
1<
1;
1:
17
06
15
14
02
01
10
1/
0-
0,
0+
b1110001101001111010000100100 J
b1110001101001111010000100100 $
#88
0(
b10011010111100 &
b11111101111101010001000001010010 #
1H
0G
1E
0D
1C
0?
0<
0;
0:
19
13
12
11
00
1-
1,
1+
1*
b11111101111101010001000001010010 J
b11111101111101010001000001010010 $
#89
b10011010111011 &
b11110010101011100010111000011001 #
1I
0H
1F
0C
1@
1?
1>
0=
1<
09
18
16
05
03
01
10
0/
0.
b11110010101011100010111000011001 J
b11110010101011100010111000011001 $
#90
1(
b10011010111010 &
b10010010010110110001101000110 #
0I
1H
1G
0F
0E
1C
1A
0?
0>
1;
19
07
04
13
02
0,
0+
0*
b10010010010110110001101000110 J
b10010010010110110001101000110 $
#91
b10011010111001 &
b11010111100001010010000000110100 #
0H
1E
1D
0C
0A
0@
0;
08
17
06
03
12
11
1/
1+
1*
b11010111100001010010000000110100 J
b11010111100001010010000000110100 $
#92
0(
b10011010111000 &
b10010101010111111000100111001 #
1I
0G
1F
1A
1=
1;
1:
18
07
16
14
01
0/
0+
0*
b10010101010111111000100111001 J
b10010101010111111000100111001 $
#93
b10011010110111 &
b10100000110010010000000100110000 #
0I
0F
0=
0<
0;
0:
08
04
13
00
0-
1,
1*
b10100000110010010000000100110000 J
b10100000110010010000000100110000 $
#94
1(
b10011010110110 &
b11111010110000001010101010110 #
1H
1G
0D
1C
1?
1=
09
15
02
11
10
1/
1.
1-
0,
0*
b11111010110000001010101010110 J
b11111010110000001010101010110 $
#95
b10011010110101 &
b1010011111110010000001100101011 #
1I
0G
1F
0E
1D
0C
1@
0?
0=
19
14
12
0/
0.
1+
b1010011111110010000001100101011 J
b1010011111110010000001100101011 $
#96
0(
b10011010110100 &
b101100110011111110100101100100 #
0I
0H
1G
0F
1C
0@
1>
1<
1;
1:
18
17
05
04
01
00
1/
1.
0-
1,
0+
b101100110011111110100101100100 J
b101100110011111110100101100100 $
#97
b10011010110011 &
b10010001010010111001011111001111 #
1I
1H
1F
0D
1B
1@
1?
0>
1=
0<
0;
07
02
11
0/
0.
1-
0,
1*
b10010001010010111001011111001111 J
b10010001010010111001011111001111 $
#98
1(
b10011010110010 &
b1111101101000111000110011000111 #
0F
0A
0@
1>
0=
06
14
03
12
1/
1.
1,
1+
0*
b1111101101000111000110011000111 J
b1111101101000111000110011000111 $
#99
b10011010110001 &
b1111001111011111011110011010 #
0I
0G
1F
1E
0C
1A
1@
0>
1=
1<
1;
08
17
16
15
02
10
0-
0,
0+
b1111001111011111011110011010 J
b1111001111011111011110011010 $
#100
0(
b10011010110000 &
b11101011110010101011000011101100 #
0H
1G
0E
1D
1C
0A
0@
0?
0;
09
18
07
05
04
13
12
0/
1,
1+
1*
b11101011110010101011000011101100 J
b11101011110010101011000011101100 $
#101
b10011010101111 &
b11010011101101100011011101011010 #
1H
0G
1E
0D
0B
1A
1@
1?
0:
17
06
15
14
03
0.
1-
0,
b11010011101101100011011101011010 J
b11010011101101100011011101011010 $
#102
1(
b10011010101110 &
b11000010110010100010010001001101 #
1I
0H
1G
0E
0A
0@
0=
07
16
05
04
13
01
0-
b11000010110010100010010001001101 J
b11000010110010100010010001001101 $
#103
b10011010101101 &
b10111111000111010100011010010001 #
0G
0F
1E
0C
1B
1@
0<
1;
19
08
17
15
03
02
11
1/
1.
1-
1,
0+
b10111111000111010100011010010001 J
b10111111000111010100011010010001 $
#104
0(
b10011010101100 &
b1001001110100111110011010110001 #
1D
1<
1:
18
07
06
13
12
00
0/
0-
0,
1+
0*
b1001001110100111110011010110001 J
b1001001110100111110011010110001 $
#105
b10011010101011 &
b10110000100011011110000001111111 #
1H
1G
1F
1C
0B
0@
0?
08
17
16
05
03
01
0.
1-
1,
0+
1*
b10110000100011011110000001111111 J
b10110000100011011110000001111111 $
#106
1(
b10011010101010 &
b10000111000000000010001001010 #
0I
0G
0E
0D
1?
0<
0;
0:
09
07
06
14
13
0,
0*
b10000111000000000010001001010 J
b10000111000000000010001001010 $
#107
b10011010101001 &
b10000111100001001111111101101001 #
1I
0H
1D
1A
1@
1>
1=
1<
1;
1:
17
04
03
11
10
1/
0-
1*
b10000111100001001111111101101001 J
b10000111100001001111111101101001 $
#108
0(
b10011010101000 &
b10000010000010011101011010000100 #
0I
1G
0F
0D
0C
1B
0A
0>
0<
19
07
16
02
01
0/
b10000010000010011101011010000100 J
b10000010000010011101011010000100 $
#109
b10011010100111 &
b11110111100101110101110111101011 #
1I
1H
0G
1F
1D
1C
1A
0@
1>
0:
18
17
06
15
12
11
1/
1-
1,
1+
b11110111100101110101110111101011 J
b11110111100101110101110111101011 $
#110
1(
b10011010100110 &
b1011010000111010001101100000111 #
1G
0F
0D
0C
0B
1@
0?
0;
08
16
02
01
0/
1.
0,
0*
b1011010000111010001101100000111 J
b1011010000111010001101100000111 $
#111
b10011010100101 &
b11110101101110001001010000011 #
0G
1B
0A
0>
18
06
14
12
1/
0+
b11110101101110001001010000011 J
b11110101101110001001010000011 $
#112
0(
b10011010100100 &
b100000100110100000010100111111 #
1G
1F
1E
1D
0B
1A
0@
1?
0=
09
07
16
04
00
0/
0.
0-
1,
b100000100110100000010100111111 J
b100000100110100000010100111111 $
#113
b10011010100011 &
b100000010111010011101101000100 #
0I
0H
0F
0E
0D
1C
1@
0?
1>
1=
1<
19
08
17
13
02
b100000010111010011101101000100 J
b100000010111010011101101000100 $
#114
1(
b10011010100010 &
b100111001111000101010011100101 #
1I
1D
1B
0A
0@
1?
0>
0<
1;
09
14
03
11
10
1/
b100111001111000101010011100101 J
b100111001111000101010011100101 $
#115
b10011010100001 &
b11011011100111010010101001011110 #
0I
1H
1F
1E
0D
0B
1@
0?
1>
0=
1<
0;
19
04
12
0/
1.
1-
0,
1+
1*
b11011011100111010010101001011110 J
b11011011100111010010101001011110 $
#116
0(
b10011010100000 &
b10010010110101100001001000000001 #
1I
0H
0G
0F
0E
0C
0>
1=
0<
09
18
06
13
01
0.
0+
b10010010110101100001001000000001 J
b10010010110101100001001000000001 $
#117
b10011010011111 &
b11111010111100011011000101100011 #
1H
1D
1C
1A
0@
1<
1:
19
08
07
14
1.
1,
1+
b11111010111100011011000101100011 J
b11111010111100011011000101100011 $
#118
1(
b10011010011110 &
b11100001010101100000001001010001 #
0H
1E
0D
0A
1@
0=
0<
0:
09
18
17
04
02
11
00
0.
0-
b11100001010101100000001001010001 J
b11100001010101100000001001010001 $
#119
b10011010011101 &
b10001011010011110100100010111101 #
1G
1F
1D
0C
1B
0@
1>
1;
19
16
05
10
1.
0,
0+
b10001011010011110100100010111101 J
b10001011010011110100100010111101 $
#120
0(
b10011010011100 &
b10111011101011000110101110100000 #
0I
0G
0F
0E
1A
1@
1<
09
08
14
03
12
1-
1,
b10111011101011000110101110100000 J
b10111011101011000110101110100000 $
#121
b10011010011011 &
b10100100000110010010111000110 #
1H
1G
0D
1C
0@
1?
0>
0;
19
18
07
06
04
01
00
1/
0.
0,
0*
b10100100000110010010111000110 J
b10100100000110010010111000110 $
#122
1(
b10011010011010 &
b10101001001011001101100101001001 #
1I
0H
0G
1F
0B
0?
1>
1=
0<
1;
1:
09
08
17
16
14
02
11
0/
1.
0-
1,
1*
b10101001001011001101100101001001 J
b10101001001011001101100101001001 $
#123
b10011010011001 &
b10010010000100010010100010010010 #
0I
1H
0F
1E
0C
1B
0A
0=
1<
0;
0:
19
07
06
15
04
01
10
0.
1-
0,
b10010010000100010010100010010010 J
b10010010000100010010100010010010 $
#124
0(
b10011010011000 &
b10000001010010100011101010101111 #
1I
1G
1F
0E
1D
1@
1=
09
18
16
05
13
11
00
0-
b10000001010010100011101010101111 J
b10000001010010100011101010101111 $
#125
b10011010010111 &
b10000101110111011001011011111111 #
1E
1C
1?
0>
0<
1:
19
08
17
15
12
1/
b10000101110111011001011011111111 J
b10000101110111011001011011111111 $
#126
1(
b10011010010110 &
b111001011101011011111010101010 #
0I
0G
0E
0C
1>
1<
06
14
02
0/
1.
1-
1,
0*
b111001011101011011111010101010 J
b111001011101011011111010101010 $
#127
b10011010010101 &
b1000111011111001100011011010010 #
0F
1E
0D
1C
0>
0=
0<
1;
09
16
10
1/
0.
0-
0,
1+
b1000111011111001100011011010010 J
b1000111011111001100011011010010 $
#128
0(
b10011010010100 &
b10101100000110110011111000000000 #
0H
0E
0C
0B
1>
1=
1<
0;
0:
19
18
07
04
03
01
00
1.
1,
0+
1*
b10101100000110110011111000000000 J
b10101100000110110011111000000000 $
#129
b10011010010011 &
b11010110110011011101011010101100 #
1G
1F
1D
1B
0>
0<
1;
1:
08
17
05
13
12
10
0.
1-
0,
1+
b11010110110011011101011010101100 J
b11010110110011011101011010101100 $
#130
1(
b10011010010010 &
b10111011010101101001001011101011 #
1I
1H
0G
1C
0?
0;
09
18
06
15
02
11
0/
1.
1,
0+
b10111011010101101001001011101011 J
b10111011010101101001001011101011 $
